{"cameraMode":{"drawMode":0,"name":"Shaded","section":"Shading Mode"},"sceneLighting":true,"audioPlay":false,"sceneViewState":{"m_AlwaysRefresh":false,"showFog":true,"showSkybox":true,"showFlares":true,"showImageEffects":true,"showParticleSystems":true,"showVisualEffectGraphs":true,"m_FxEnabled":true},"in2DMode":false,"pivot":{"x":-2.3497581481933595,"y":0.2616863250732422,"z":-5.036855697631836},"rotation":{"x":0.12740056216716767,"y":0.8695309162139893,"z":-0.37584468722343447,"w":0.2961457669734955},"size":12.12435531616211,"orthographic":false}